README.rst
nbrun.py
setup.py
nbrun.egg-info/PKG-INFO
nbrun.egg-info/SOURCES.txt
nbrun.egg-info/dependency_links.txt
nbrun.egg-info/entry_points.txt
nbrun.egg-info/requires.txt
nbrun.egg-info/top_level.txt