Metadata-Version: 1.0
Name: nbrun
Version: 0.1.0
Summary: Verify that notebooks are runnable.
Home-page: https://github.com/elgehelge/nbrun
Author: Helge Munk Jacobsen
Author-email: helgemunkjacobsen@gmail.com
License: UNKNOWN
Keywords: jupyter notebook test run runnable
Platform: UNKNOWN
